unwrapper/__init__.py
unwrapper/main.py
unwrap_basemodel_fields-0.5.1.dist-info/LICENSE
unwrap_basemodel_fields-0.5.1.dist-info/WHEEL
unwrap_basemodel_fields-0.5.1.dist-info/METADATA
unwrap_basemodel_fields-0.5.1.dist-info/RECORD
