Metadata-Version: 2.1
Name: unwrap-basemodel-fields
Version: 0.5.1
Summary: Unwrapper stores a Result object to implement unpacking of values if they are not None. The BaseModel object is also a little extended to work with the Result object.
Home-page: https://github.com/luwqz1/unwrap_basemodel_fields
License: MIT
Keywords: python,uwrapping,optional handle,basemodel fields
Author: Georgy howl
Author-email: howluwqz1@gmail.com
Requires-Python: >=3.8,<4.0
Classifier: Framework :: Pydantic
Classifier: License :: OSI Approved :: MIT License
Classifier: Programming Language :: Python :: 3
Classifier: Programming Language :: Python :: 3.8
Classifier: Programming Language :: Python :: 3.9
Classifier: Programming Language :: Python :: 3.10
Classifier: Programming Language :: Python :: 3.11
Classifier: Programming Language :: Python :: 3 :: Only
Classifier: Topic :: Internet
Classifier: Topic :: Software Development :: Libraries :: Python Modules
Classifier: Typing :: Typed
Requires-Dist: pydantic (>=1.9.0,<2.0.0)
Project-URL: Repository, https://github.com/luwqz1/unwrap_basemodel_fields
